graphite_bridge/__init__.py
graphite_bridge/base_strategy.py
graphite_bridge/server.py
graphite_bridge/exchanges/__init__.py
graphite_bridge/exchanges/router.py
graphite_bridge-0.2.2.dist-info/LICENSE
graphite_bridge-0.2.2.dist-info/METADATA
graphite_bridge-0.2.2.dist-info/WHEEL
graphite_bridge-0.2.2.dist-info/top_level.txt
graphite_bridge-0.2.2.dist-info/RECORD
