Metadata-Version: 2.1
Name: graphite-bridge
Version: 0.2.2
Summary: Graphite Bridge
Home-page: UNKNOWN
Author: Jonathan Wengel
Author-email: <jonthan.anodaram@gmail.com>
License: UNKNOWN
Keywords: python,graphite,trading,cryptocurrency
Platform: UNKNOWN
Classifier: Development Status :: 1 - Planning
Classifier: Intended Audience :: Developers
Classifier: Programming Language :: Python :: 3
Classifier: Operating System :: Unix
Classifier: Operating System :: MacOS :: MacOS X
Classifier: Operating System :: Microsoft :: Windows
License-File: LICENSE
Requires-Dist: requests
Requires-Dist: websocket-client
